mnkgame/Board.py
mnkgame/BoardGravity.py
mnkgame/GameAi.py
mnkgame/GameAiRandom.py
mnkgame/GameAiSearchTree.py
mnkgame/__init__.py
mnkgame/_version.py
mnkgame/mnk_game.py
mnkgame/mnk_game_cli.py
mnkgame/mnk_game_gui.py
mnkgame/mnk_game_tui.py
mnkgame/util.py
mnkgame/resources/__init__.py
mnkgame-0.0.0.5.data/data/share/icons/mnkgame_logo.svg
mnkgame-0.0.0.5.data/data/share/icons/piece_o.svg
mnkgame-0.0.0.5.data/data/share/icons/piece_x.svg
mnkgame-0.0.0.5.dist-info/DESCRIPTION.rst
mnkgame-0.0.0.5.dist-info/METADATA
mnkgame-0.0.0.5.dist-info/RECORD
mnkgame-0.0.0.5.dist-info/WHEEL
mnkgame-0.0.0.5.dist-info/entry_points.txt
mnkgame-0.0.0.5.dist-info/metadata.json
mnkgame-0.0.0.5.dist-info/top_level.txt
