Metadata-Version: 2.0
Name: mnkgame
Version: 0.0.0.5
Summary: Library and user interfaces for (m,n,k)+g?-games.
Home-page: https://github.com/norok2/mnkgame
Author: Riccardo Metere
Author-email: rick@metere.it
License: GPLv3+
Keywords: geometry,geometric,raster,shape,pixel,voxel,render,mask
Platform: UNKNOWN
Classifier: Development Status :: 4 - Beta
Classifier: Intended Audience :: Developers
Classifier: Intended Audience :: End Users/Desktop
Classifier: Intended Audience :: Science/Research
Classifier: Intended Audience :: Education
Classifier: Natural Language :: English
Classifier: Topic :: Software Development
Classifier: Topic :: Software Development :: Libraries
Classifier: Topic :: Utilities
Classifier: Operating System :: POSIX
Classifier: License :: OSI Approved :: GNU General Public License v3 or later (GPLv3+)
Classifier: Programming Language :: Python
Classifier: Programming Language :: Python :: 3
Provides-Extra: blessings
Requires-Dist: appdirs
Requires-Dist: asciimatics
Requires-Dist: blessed
Requires-Dist: numpy
Requires-Dist: scipy
Requires-Dist: setuptools
Provides-Extra: blessings
Requires-Dist: blessings; extra == 'blessings'
